dynamic_preferences/__init__.py
dynamic_preferences/admin.py
dynamic_preferences/apps.py
dynamic_preferences/exceptions.py
dynamic_preferences/forms.py
dynamic_preferences/managers.py
dynamic_preferences/models.py
dynamic_preferences/preferences.py
dynamic_preferences/processors.py
dynamic_preferences/registries.py
dynamic_preferences/serializers.py
dynamic_preferences/settings.py
dynamic_preferences/signals.py
dynamic_preferences/types.py
dynamic_preferences/urls.py
dynamic_preferences/utils.py
dynamic_preferences/views.py
dynamic_preferences/api/__init__.py
dynamic_preferences/api/serializers.py
dynamic_preferences/api/viewsets.py
dynamic_preferences/locale/ar/LC_MESSAGES/django.mo
dynamic_preferences/locale/ar/LC_MESSAGES/django.po
dynamic_preferences/locale/de/LC_MESSAGES/django.mo
dynamic_preferences/locale/de/LC_MESSAGES/django.po
dynamic_preferences/locale/fr/LC_MESSAGES/django.mo
dynamic_preferences/locale/fr/LC_MESSAGES/django.po
dynamic_preferences/locale/id/LC_MESSAGES/django.mo
dynamic_preferences/locale/id/LC_MESSAGES/django.po
dynamic_preferences/locale/pl/LC_MESSAGES/django.mo
dynamic_preferences/locale/pl/LC_MESSAGES/django.po
dynamic_preferences/management/__init__.py
dynamic_preferences/management/commands/__init__.py
dynamic_preferences/management/commands/checkpreferences.py
dynamic_preferences/migrations/0001_initial.py
dynamic_preferences/migrations/0002_auto_20150712_0332.py
dynamic_preferences/migrations/0003_auto_20151223_1407.py
dynamic_preferences/migrations/0004_move_user_model.py
dynamic_preferences/migrations/0005_auto_20181120_0848.py
dynamic_preferences/migrations/0006_auto_20191001_2236.py
dynamic_preferences/migrations/__init__.py
dynamic_preferences/templates/dynamic_preferences/base.html
dynamic_preferences/templates/dynamic_preferences/form.html
dynamic_preferences/templates/dynamic_preferences/sections.html
dynamic_preferences/templates/dynamic_preferences/testcontext.html
dynamic_preferences/users/__init__.py
django_dynamic_preferences-1.17.0.dist-info/AUTHORS.rst
django_dynamic_preferences-1.17.0.dist-info/LICENSE
django_dynamic_preferences-1.17.0.dist-info/METADATA
django_dynamic_preferences-1.17.0.dist-info/WHEEL
django_dynamic_preferences-1.17.0.dist-info/top_level.txt
django_dynamic_preferences-1.17.0.dist-info/RECORD
