Metadata-Version: 2.2
Name: django-dynamic-preferences
Version: 1.17.0
Summary: Dynamic global and instance settings for your django project
Home-page: https://github.com/agateblue/django-dynamic-preferences
Author: Agate Blue
Author-email: me+github@agate.blue
License: BSD
Keywords: django-dynamic-preferences
Classifier: Development Status :: 5 - Production/Stable
Classifier: Framework :: Django
Classifier: Intended Audience :: Developers
Classifier: License :: OSI Approved :: BSD License
Classifier: Natural Language :: English
Classifier: Programming Language :: Python :: 3
License-File: LICENSE
License-File: AUTHORS.rst
Requires-Dist: django>=4.2
Requires-Dist: persisting_theory==1.0
Dynamic: author
Dynamic: author-email
Dynamic: classifier
Dynamic: description
Dynamic: home-page
Dynamic: keywords
Dynamic: license
Dynamic: requires-dist
Dynamic: summary
